python_vor/__init__.py
python_vor/classes.py
python_vor/python_vor.py
python_vor/utils.py
python_vor-0.0.5.dist-info/licenses/CODE_OF_CONDUCT.md
python_vor-0.0.5.dist-info/licenses/CONTRIBUTING.md
python_vor-0.0.5.dist-info/licenses/LICENSE
python_vor-0.0.5.dist-info/licenses/README.md
python_vor-0.0.5.dist-info/METADATA
python_vor-0.0.5.dist-info/WHEEL
python_vor-0.0.5.dist-info/top_level.txt
python_vor-0.0.5.dist-info/RECORD
