Metadata-Version: 2.4
Name: python-vor
Version: 0.0.5
Summary: A small library to calculate the bearing of a VOR signal from a WAV file.
Author-email: Luca Bennati <lucabennati1996@gmail.com>
Project-URL: Homepage, https://github.com/iu2frl/python_vor
Project-URL: Source, https://github.com/iu2frl/python_vor
Project-URL: Issues, https://github.com/iu2frl/python_vor/issues
Keywords: vor,bearing,airports,location,navigation,signal processing
Classifier: Development Status :: 4 - Beta
Classifier: Intended Audience :: Developers
Classifier: Programming Language :: Python
Classifier: Programming Language :: Python :: 3
Classifier: Programming Language :: Python :: 3.10
Classifier: Programming Language :: Python :: 3.11
Classifier: Programming Language :: Python :: 3.12
Classifier: Operating System :: OS Independent
Requires-Python: >=3.8
License-File: LICENSE
License-File: CODE_OF_CONDUCT.md
License-File: README.md
License-File: CONTRIBUTING.md
Requires-Dist: scipy==1.16.0
Requires-Dist: numpy==2.3.1
Dynamic: license-file
